reversion_compare/__init__.py
reversion_compare/admin.py
reversion_compare/apps.py
reversion_compare/checks.py
reversion_compare/compare.py
reversion_compare/compare_raw.py
reversion_compare/constants.py
reversion_compare/context_processors.py
reversion_compare/exceptions.py
reversion_compare/forms.py
reversion_compare/helpers.py
reversion_compare/mixins.py
reversion_compare/models.py
reversion_compare/publish.py
reversion_compare/views.py
reversion_compare/locale/de/LC_MESSAGES/django.mo
reversion_compare/locale/de/LC_MESSAGES/django.po
reversion_compare/locale/el/LC_MESSAGES/django.mo
reversion_compare/locale/el/LC_MESSAGES/django.po
reversion_compare/locale/fi/LC_MESSAGES/django.mo
reversion_compare/locale/fi/LC_MESSAGES/django.po
reversion_compare/locale/fr/LC_MESSAGES/django.mo
reversion_compare/locale/fr/LC_MESSAGES/django.po
reversion_compare/locale/nl/LC_MESSAGES/django.mo
reversion_compare/locale/nl/LC_MESSAGES/django.po
reversion_compare/locale/pl/LC_MESSAGES/django.mo
reversion_compare/locale/pl/LC_MESSAGES/django.po
reversion_compare/static/reversion_compare.css
reversion_compare/templates/reversion-compare/action_list_partial.html
reversion_compare/templates/reversion-compare/compare.html
reversion_compare/templates/reversion-compare/compare_BooleanField.html
reversion_compare/templates/reversion-compare/compare_DateTimeField.html
reversion_compare/templates/reversion-compare/compare_generic_add.html
reversion_compare/templates/reversion-compare/compare_generic_many_to_many.html
reversion_compare/templates/reversion-compare/compare_generic_remove.html
reversion_compare/templates/reversion-compare/compare_links_partial.html
reversion_compare/templates/reversion-compare/compare_partial.html
reversion_compare/templates/reversion-compare/compare_raw.html
reversion_compare/templates/reversion-compare/compare_raw_partial.html
reversion_compare/templates/reversion-compare/object_history.html
reversion_compare/tests/__init__.py
django_reversion_compare-0.19.1.dist-info/METADATA
django_reversion_compare-0.19.1.dist-info/WHEEL
django_reversion_compare-0.19.1.dist-info/entry_points.txt
django_reversion_compare-0.19.1.dist-info/licenses/LICENSE
django_reversion_compare-0.19.1.dist-info/RECORD
