Metadata-Version: 2.4
Name: django-reversion-compare
Version: 0.19.1
Summary: Add compare view to django-reversion for comparing two versions of a reversion model.
Project-URL: Documentation, https://github.com/jedie/django-reversion-compare
Project-URL: Source, https://github.com/jedie/django-reversion-compare
Author-email: Jens Diemer <django-reversion-compare@jensdiemer.de>
License: GPL-3.0-or-later
License-File: LICENSE
Requires-Python: >=3.11
Requires-Dist: diff-match-patch
Requires-Dist: django
Requires-Dist: django-reversion
Requires-Dist: rich
